Metadata-Version: 2.1
Name: django-chit-chat
Version: 0.0.10
Summary: chat for projects we help maintain @ ckc
Home-page: https://github.com/ckc-org/django-chit-chat
Author: Bailey Trefts
Author-email: bailey@ckcollab.com
Keywords: django
Classifier: Development Status :: 4 - Beta
Classifier: Intended Audience :: Developers
Classifier: Programming Language :: Python :: 3.8
Classifier: Topic :: Software Development
Requires-Python: >=3.8
License-File: LICENSE
